{
  "basic_apply": [
    {
      "name": "团队分红",
      "logo": "",
      "sign": "bonus",
      "desc": "这是团队分红插件",
      "content": "这是团队分红插件1111",
      "version": "1.0.0"
    },
    {
      "name": "股东分红",
      "logo": "",
      "sign": "stock",
      "desc": "这是股东分红插件",
      "content": "这是股东分红插件",
      "version": "1.0.0"
    },
    {
      "name": "区域分红",
      "logo": "",
      "sign": "region",
      "desc": "这是区域分红插件",
      "content": "这是区域分红插件",
      "version": "1.0.0"
    }
  ],
  "market_apply": [
    {
      "name": "拼团",
      "logo": "",
      "sign": "拼团",
      "desc": "这是拼团插件",
      "content": "这是拼团插件",
      "version": "1.0.0"
    }
  ],
  "channel": [
    {
      "name": "微信小程序",
      "logo": "",
      "sign": "wechat",
      "desc": "微信小程序渠道",
      "content": "微信小程序渠道",
      "version": "1.0.0"
    },
    {
      "name": "微信公众号",
      "logo": "",
      "sign": "mp",
      "desc": "微信公众号渠道",
      "content": "微信公众号渠道",
      "version": "1.0.0"
    },
    {
      "name": "支付宝小程序",
      "logo": "",
      "sign": "alipay",
      "desc": "支付宝小程序",
      "content": "支付宝小程序",
      "version": "1.0.0"
    }
  ]
}